nonebot_plugin_anywhere_llm/__init__.py
nonebot_plugin_anywhere_llm/config.py
nonebot_plugin_anywhere_llm/llm_service.py
nonebot_plugin_anywhere_llm/message_handle/__init__.py
nonebot_plugin_anywhere_llm/message_handle/history_manager.py
nonebot_plugin_anywhere_llm/message_handle/injectors/__init__.py
nonebot_plugin_anywhere_llm/message_handle/message_handle.py
nonebot_plugin_anywhere_llm/message_handle/prompt_templates.py
nonebot_plugin_anywhere_llm/message_handle/tools.py
nonebot_plugin_anywhere_llm/provider/__init__.py
nonebot_plugin_anywhere_llm/provider/interface.py
nonebot_plugin_anywhere_llm/provider/openai.py
nonebot_plugin_anywhere_llm/test/__init__.py
nonebot_plugin_anywhere_llm/utils/__init__.py
nonebot_plugin_anywhere_llm/utils/logging.py
nonebot_plugin_anywhere_llm-1.1.6.dist-info/LICENSE
nonebot_plugin_anywhere_llm-1.1.6.dist-info/METADATA
nonebot_plugin_anywhere_llm-1.1.6.dist-info/WHEEL
nonebot_plugin_anywhere_llm-1.1.6.dist-info/RECORD
